{"stock_id":"5347","entries":[{"date":"20251027","open":103.5,"high":106.5,"low":102.0,"close":102.5,"volume":14560604},{"date":"20251028","open":103.0,"high":103.0,"low":99.6,"close":99.6,"volume":8158005},{"date":"20251029","open":100.5,"high":101.5,"low":98.4,"close":99.0,"volume":7202158},{"date":"20251030","open":100.0,"high":100.0,"low":97.4,"close":98.0,"volume":7333473},{"date":"20251031","open":98.0,"high":98.3,"low":96.1,"close":96.7,"volume":10833030},{"date":"20251103","open":97.0,"high":99.6,"low":96.8,"close":97.2,"volume":5242974},{"date":"20251104","open":97.8,"high":103.0,"low":97.6,"close":98.7,"volume":14929935},{"date":"20251105","open":97.0,"high":97.5,"low":93.6,"close":96.0,"volume":13783989},{"date":"20251106","open":96.4,"high":96.5,"low":94.0,"close":94.2,"volume":11572956},{"date":"20251107","open":93.8,"high":94.2,"low":92.0,"close":93.0,"volume":5860624},{"date":"20251110","open":92.9,"high":93.5,"low":91.5,"close":92.0,"volume":6192625},{"date":"20251111","open":93.2,"high":94.0,"low":92.1,"close":92.2,"volume":5192326},{"date":"20251112","open":94.0,"high":95.3,"low":92.5,"close":92.5,"volume":6868378},{"date":"20251113","open":92.3,"high":93.1,"low":91.7,"close":92.5,"volume":5391824},{"date":"20251114","open":91.7,"high":92.1,"low":90.4,"close":90.6,"volume":6810532},{"date":"20251117","open":90.6,"high":91.5,"low":90.2,"close":90.5,"volume":4813617},{"date":"20251118","open":89.9,"high":90.6,"low":89.2,"close":89.6,"volume":6558801},{"date":"20251119","open":89.0,"high":89.5,"low":87.6,"close":88.0,"volume":6803675},{"date":"20251120","open":89.0,"high":91.4,"low":88.9,"close":89.8,"volume":5912947},{"date":"20251121","open":88.8,"high":89.6,"low":87.6,"close":88.6,"volume":6302394},{"date":"20251124","open":89.2,"high":89.6,"low":87.8,"close":88.0,"volume":6443334},{"date":"20251125","open":89.0,"high":90.3,"low":88.8,"close":90.1,"volume":4999995},{"date":"20251126","open":90.9,"high":91.4,"low":89.5,"close":90.2,"volume":4452891},{"date":"20251127","open":90.5,"high":91.1,"low":90.2,"close":91.1,"volume":3729548},{"date":"20251128","open":91.0,"high":91.3,"low":90.5,"close":90.5,"volume":2746959},{"date":"20251201","open":91.0,"high":92.3,"low":90.6,"close":91.5,"volume":5197085},{"date":"20251202","open":91.7,"high":93.0,"low":91.1,"close":92.5,"volume":5054035},{"date":"20251203","open":93.1,"high":93.1,"low":91.1,"close":91.2,"volume":3442737},{"date":"20251204","open":91.4,"high":92.0,"low":91.0,"close":91.3,"volume":2352290},{"date":"20251205","open":91.3,"high":92.3,"low":91.1,"close":92.3,"volume":1592066},{"date":"20251208","open":92.3,"high":93.4,"low":92.0,"close":92.5,"volume":2928184},{"date":"20251209","open":92.5,"high":93.2,"low":92.0,"close":92.0,"volume":2866841},{"date":"20251210","open":92.5,"high":92.7,"low":91.9,"close":92.6,"volume":1949946},{"date":"20251211","open":93.0,"high":93.4,"low":91.8,"close":91.9,"volume":2910258},{"date":"20251212","open":91.9,"high":92.4,"low":90.8,"close":90.8,"volume":3531390},{"date":"20251215","open":90.1,"high":91.7,"low":89.5,"close":91.3,"volume":3569405},{"date":"20251216","open":90.8,"high":92.6,"low":89.8,"close":92.3,"volume":5059361},{"date":"20251217","open":92.3,"high":97.2,"low":92.1,"close":95.9,"volume":16193632},{"date":"20251218","open":95.0,"high":97.0,"low":94.7,"close":96.9,"volume":7493581},{"date":"20251219","open":97.9,"high":97.9,"low":95.6,"close":96.3,"volume":4398998},{"date":"20251222","open":95.7,"high":97.4,"low":95.5,"close":97.4,"volume":4756328},{"date":"20251223","open":97.6,"high":98.6,"low":97.5,"close":98.6,"volume":6593290},{"date":"20251224","open":99.0,"high":99.6,"low":97.7,"close":99.2,"volume":5659297},{"date":"20251226","open":99.5,"high":100.0,"low":97.7,"close":98.2,"volume":8794753},{"date":"20251229","open":98.2,"high":98.2,"low":95.6,"close":96.0,"volume":9787636},{"date":"20251230","open":95.5,"high":96.9,"low":94.1,"close":94.5,"volume":8646397},{"date":"20251231","open":95.0,"high":95.0,"low":91.8,"close":92.1,"volume":9752642},{"date":"20260102","open":92.5,"high":93.2,"low":92.0,"close":92.3,"volume":8365004},{"date":"20260105","open":92.4,"high":93.7,"low":91.5,"close":93.2,"volume":10398895},{"date":"20260106","open":93.6,"high":101.0,"low":93.5,"close":99.5,"volume":27137932},{"date":"20260107","open":100.0,"high":105.0,"low":97.3,"close":103.5,"volume":37506915},{"date":"20260108","open":104.0,"high":113.5,"low":102.0,"close":109.0,"volume":99986643},{"date":"20260109","open":111.0,"high":115.0,"low":108.0,"close":108.5,"volume":63634410},{"date":"20260112","open":114.0,"high":119.0,"low":112.0,"close":119.0,"volume":69401002},{"date":"20260113","open":118.5,"high":122.0,"low":114.0,"close":117.5,"volume":65250789},{"date":"20260114","open":122.5,"high":129.0,"low":122.0,"close":124.0,"volume":71968975},{"date":"20260115","open":125.5,"high":127.5,"low":122.0,"close":127.0,"volume":34678103},{"date":"20260116","open":130.5,"high":139.5,"low":128.0,"close":139.5,"volume":79389306},{"date":"20260119","open":142.5,"high":145.0,"low":137.5,"close":139.0,"volume":56101665},{"date":"20260120","open":139.0,"high":143.5,"low":134.5,"close":141.5,"volume":52292020},{"date":"20260121","open":141.5,"high":154.5,"low":140.5,"close":146.5,"volume":54050034},{"date":"20260122","open":152.0,"high":155.0,"low":144.0,"close":145.5,"volume":42941021},{"date":"20260123","open":148.0,"high":150.0,"low":142.0,"close":146.5,"volume":34448633},{"date":"20260126","open":145.0,"high":147.5,"low":140.5,"close":145.0,"volume":27321148},{"date":"20260127","open":152.0,"high":159.5,"low":148.5,"close":159.5,"volume":40282610},{"date":"20260128","open":165.0,"high":171.0,"low":161.0,"close":163.0,"volume":62557073},{"date":"20260129","open":158.0,"high":160.0,"low":147.0,"close":147.0,"volume":43958510},{"date":"20260130","open":147.0,"high":148.0,"low":135.0,"close":143.5,"volume":69466600},{"date":"20260202","open":140.5,"high":142.0,"low":133.0,"close":136.5,"volume":35517149},{"date":"20260203","open":142.5,"high":142.5,"low":133.0,"close":135.5,"volume":36055353},{"date":"20260204","open":124.5,"high":126.5,"low":122.0,"close":122.0,"volume":43267877},{"date":"20260205","open":120.5,"high":121.0,"low":112.0,"close":113.5,"volume":42840949},{"date":"20260206","open":115.0,"high":123.0,"low":113.0,"close":120.0,"volume":57406798},{"date":"20260209","open":123.5,"high":130.0,"low":122.5,"close":126.0,"volume":64768506},{"date":"20260210","open":130.0,"high":131.0,"low":124.5,"close":124.5,"volume":42922870},{"date":"20260211","open":125.0,"high":126.5,"low":123.5,"close":126.0,"volume":12973838},{"date":"20260223","open":127.0,"high":130.0,"low":125.0,"close":125.0,"volume":32880614},{"date":"20260224","open":125.5,"high":137.5,"low":123.5,"close":137.5,"volume":45077643},{"date":"20260225","open":139.0,"high":140.5,"low":133.0,"close":135.0,"volume":36508816},{"date":"20260226","open":136.5,"high":136.5,"low":132.5,"close":133.5,"volume":16437264},{"date":"20260302","open":127.0,"high":132.0,"low":126.5,"close":129.5,"volume":23095201},{"date":"20260303","open":130.5,"high":134.0,"low":122.0,"close":123.0,"volume":32654046},{"date":"20260304","open":119.0,"high":121.0,"low":114.0,"close":116.0,"volume":23190040},{"date":"20260305","open":122.5,"high":123.0,"low":117.0,"close":119.5,"volume":14596606},{"date":"20260306","open":118.0,"high":120.5,"low":116.5,"close":118.5,"volume":9327694},{"date":"20260309","open":109.0,"high":111.0,"low":107.0,"close":110.0,"volume":22791076},{"date":"20260310","open":113.0,"high":114.0,"low":110.0,"close":111.5,"volume":18194427},{"date":"20260311","open":112.5,"high":115.0,"low":111.5,"close":114.0,"volume":15693118},{"date":"20260312","open":113.5,"high":114.5,"low":107.0,"close":107.5,"volume":27454363},{"date":"20260313","open":105.0,"high":114.5,"low":105.0,"close":114.0,"volume":22003731},{"date":"20260316","open":115.0,"high":116.5,"low":112.0,"close":116.0,"volume":16453329},{"date":"20260317","open":118.5,"high":124.0,"low":117.0,"close":118.5,"volume":27967511},{"date":"20260318","open":119.5,"high":123.0,"low":117.0,"close":121.0,"volume":17837828},{"date":"20260319","open":119.0,"high":121.5,"low":117.5,"close":117.5,"volume":15446925},{"date":"20260320","open":120.0,"high":120.5,"low":113.5,"close":116.0,"volume":16831543},{"date":"20260323","open":112.0,"high":115.0,"low":111.0,"close":113.0,"volume":10146951},{"date":"20260324","open":115.5,"high":117.5,"low":111.5,"close":113.0,"volume":9888182},{"date":"20260325","open":116.5,"high":124.0,"low":116.0,"close":124.0,"volume":17569430},{"date":"20260326","open":127.5,"high":128.0,"low":117.0,"close":117.0,"volume":25463253},{"date":"20260327","open":118.0,"high":122.0,"low":115.5,"close":120.5,"volume":21227532},{"date":"20260330","open":117.5,"high":119.5,"low":113.5,"close":117.0,"volume":16882786},{"date":"20260331","open":115.0,"high":119.0,"low":113.0,"close":116.0,"volume":16490032},{"date":"20260401","open":122.0,"high":122.5,"low":117.0,"close":118.0,"volume":14920754},{"date":"20260402","open":118.5,"high":118.5,"low":110.0,"close":110.0,"volume":26102933},{"date":"20260407","open":114.0,"high":121.0,"low":112.5,"close":121.0,"volume":23648364},{"date":"20260408","open":125.5,"high":132.5,"low":125.5,"close":131.0,"volume":36749881},{"date":"20260409","open":133.0,"high":133.0,"low":128.5,"close":131.5,"volume":19165246},{"date":"20260410","open":133.5,"high":133.5,"low":128.0,"close":129.0,"volume":19753578},{"date":"20260413","open":128.0,"high":128.0,"low":124.0,"close":125.5,"volume":19347625},{"date":"20260414","open":127.5,"high":128.0,"low":124.5,"close":124.5,"volume":12094075},{"date":"20260415","open":127.0,"high":130.5,"low":126.0,"close":127.5,"volume":19355493},{"date":"20260416","open":133.0,"high":139.5,"low":130.0,"close":132.5,"volume":48689384},{"date":"20260417","open":132.5,"high":137.0,"low":129.0,"close":132.0,"volume":29439248},{"date":"20260420","open":134.5,"high":145.0,"low":134.0,"close":139.0,"volume":69492865},{"date":"20260421","open":138.0,"high":143.0,"low":136.0,"close":138.5,"volume":47840852},{"date":"20260422","open":141.0,"high":151.0,"low":141.0,"close":145.0,"volume":71683948},{"date":"20260423","open":147.0,"high":147.5,"low":133.5,"close":136.0,"volume":46214225},{"date":"20260424","open":140.0,"high":146.0,"low":139.0,"close":140.5,"volume":37995857},{"date":"20260427","open":141.0,"high":143.5,"low":133.5,"close":138.5,"volume":32098190},{"date":"20260428","open":142.0,"high":149.5,"low":139.0,"close":146.0,"volume":49099656},{"date":"20260429","open":147.0,"high":150.0,"low":143.0,"close":144.0,"volume":35091140},{"date":"20260430","open":147.5,"high":152.5,"low":144.0,"close":145.5,"volume":43741395},{"date":"20260504","open":147.5,"high":157.5,"low":147.5,"close":151.0,"volume":42290102.0},{"date":"20260506","open":150.5,"high":157.5,"low":148.5,"close":154.0,"volume":37890514.0},{"date":"20260507","open":169.0,"high":169.0,"low":165.5,"close":169.0,"volume":55462570.0},{"date":"20260508","open":178.5,"high":184.5,"low":167.0,"close":167.5,"volume":69119549.0},{"date":"20260511","open":169.0,"high":180.0,"low":163.5,"close":174.5,"volume":48925865.0},{"date":"20260512","open":174.0,"high":175.0,"low":164.5,"close":170.0,"volume":48959955.0},{"date":"20260513","open":167.5,"high":172.0,"low":164.5,"close":168.0,"volume":24475608.0},{"date":"20260514","open":170.0,"high":179.0,"low":166.5,"close":175.0,"volume":39662990.0},{"date":"20260515","open":181.0,"high":183.5,"low":173.0,"close":176.5,"volume":49783035.0},{"date":"20260518","open":159.0,"high":161.0,"low":159.0,"close":159.0,"volume":169493712.0},{"date":"20260519","open":159.5,"high":165.5,"low":152.5,"close":157.5,"volume":102682134.0},{"date":"20260520","open":160.5,"high":162.0,"low":156.0,"close":159.0,"volume":45145519.0},{"date":"20260522","open":165.0,"high":167.5,"low":158.0,"close":162.0,"volume":30767508.0}],"market":"上櫃","last_updated":"20260522124009"}