{"stock_id":"6770","entries":[{"date":"20240506","open":25.7,"high":25.9,"low":25.05,"close":25.2,"volume":45471714},{"date":"20240507","open":25.2,"high":25.4,"low":24.6,"close":24.7,"volume":26073976},{"date":"20240508","open":24.75,"high":25.1,"low":24.35,"close":24.7,"volume":20244030},{"date":"20240509","open":25.05,"high":25.2,"low":24.7,"close":24.75,"volume":15855023},{"date":"20240510","open":24.75,"high":24.9,"low":24.15,"close":24.35,"volume":14354210},{"date":"20240513","open":24.35,"high":24.35,"low":23.9,"close":24.1,"volume":15763527},{"date":"20240514","open":24.6,"high":25.25,"low":24.55,"close":24.85,"volume":21925679},{"date":"20240515","open":24.55,"high":24.85,"low":24.3,"close":24.7,"volume":25831992},{"date":"20240516","open":24.9,"high":26.75,"low":24.9,"close":26.45,"volume":80681492},{"date":"20240517","open":26.7,"high":26.75,"low":25.65,"close":25.65,"volume":42453685},{"date":"20240520","open":26.2,"high":26.2,"low":25.25,"close":25.45,"volume":24833460},{"date":"20240521","open":25.45,"high":25.8,"low":25.3,"close":25.55,"volume":12496618},{"date":"20240522","open":25.5,"high":26.7,"low":25.5,"close":26.15,"volume":34810495},{"date":"20240523","open":26.4,"high":26.8,"low":26.1,"close":26.55,"volume":37759821},{"date":"20240524","open":26.1,"high":26.1,"low":25.35,"close":25.65,"volume":31228581},{"date":"20240527","open":25.6,"high":26.3,"low":25.6,"close":25.95,"volume":30149469},{"date":"20240528","open":26.0,"high":26.4,"low":25.6,"close":26.35,"volume":31174189},{"date":"20240529","open":26.35,"high":26.35,"low":25.8,"close":25.8,"volume":19424490},{"date":"20240530","open":25.55,"high":25.9,"low":25.4,"close":25.4,"volume":21555668},{"date":"20240531","open":25.45,"high":26.1,"low":24.65,"close":24.9,"volume":299505430},{"date":"20240603","open":25.25,"high":25.55,"low":24.7,"close":24.75,"volume":24184600},{"date":"20240604","open":24.5,"high":24.65,"low":24.25,"close":24.25,"volume":16929597},{"date":"20240605","open":24.4,"high":24.55,"low":23.9,"close":24.3,"volume":19152584},{"date":"20240606","open":24.45,"high":24.75,"low":24.1,"close":24.15,"volume":13292288},{"date":"20240607","open":24.3,"high":24.9,"low":24.3,"close":24.75,"volume":17743733},{"date":"20240611","open":24.8,"high":25.9,"low":24.8,"close":25.2,"volume":30059333},{"date":"20240612","open":25.3,"high":25.5,"low":24.85,"close":25.25,"volume":21817636},{"date":"20240613","open":26.0,"high":26.75,"low":26.0,"close":26.2,"volume":63422843},{"date":"20240614","open":26.25,"high":26.75,"low":25.95,"close":26.7,"volume":44242010},{"date":"20240617","open":26.85,"high":28.5,"low":26.6,"close":27.8,"volume":93896893},{"date":"20240618","open":28.05,"high":28.15,"low":27.2,"close":27.55,"volume":44208657},{"date":"20240619","open":27.6,"high":27.7,"low":26.65,"close":26.7,"volume":38477436},{"date":"20240620","open":26.8,"high":28.0,"low":26.8,"close":27.6,"volume":49206296},{"date":"20240621","open":27.45,"high":27.8,"low":27.2,"close":27.6,"volume":24765478},{"date":"20240624","open":27.6,"high":27.6,"low":26.75,"close":26.85,"volume":22933506},{"date":"20240625","open":26.9,"high":27.1,"low":26.3,"close":26.55,"volume":14973801},{"date":"20240626","open":26.6,"high":26.75,"low":26.0,"close":26.35,"volume":16511680},{"date":"20240627","open":26.35,"high":26.4,"low":26.0,"close":26.1,"volume":11755778},{"date":"20240628","open":26.3,"high":26.95,"low":26.3,"close":26.8,"volume":16987972},{"date":"20240701","open":27.0,"high":27.6,"low":26.9,"close":27.15,"volume":26183052},{"date":"20240702","open":27.1,"high":27.2,"low":26.7,"close":26.7,"volume":17914732},{"date":"20240703","open":27.0,"high":27.2,"low":26.8,"close":26.9,"volume":11785701},{"date":"20240704","open":27.2,"high":27.4,"low":26.7,"close":26.95,"volume":16631484},{"date":"20240705","open":26.95,"high":27.2,"low":26.65,"close":26.8,"volume":11665887},{"date":"20240708","open":26.9,"high":27.3,"low":26.55,"close":26.75,"volume":16564624},{"date":"20240709","open":26.85,"high":26.85,"low":26.0,"close":26.45,"volume":22350548},{"date":"20240710","open":26.45,"high":26.5,"low":26.05,"close":26.15,"volume":12559565},{"date":"20240711","open":26.5,"high":26.85,"low":26.3,"close":26.65,"volume":15203057},{"date":"20240712","open":26.5,"high":26.9,"low":26.25,"close":26.45,"volume":12198157},{"date":"20240715","open":26.55,"high":26.65,"low":25.7,"close":25.75,"volume":25045070},{"date":"20240716","open":25.9,"high":26.25,"low":25.65,"close":25.65,"volume":15256408},{"date":"20240717","open":24.35,"high":25.3,"low":23.6,"close":24.75,"volume":63369685},{"date":"20240718","open":24.1,"high":24.35,"low":23.8,"close":24.15,"volume":38423833},{"date":"20240719","open":24.2,"high":24.2,"low":23.7,"close":23.7,"volume":24010648},{"date":"20240722","open":23.75,"high":23.75,"low":23.0,"close":23.2,"volume":22775219},{"date":"20240723","open":23.35,"high":23.7,"low":23.25,"close":23.3,"volume":15656780},{"date":"20240726","open":22.8,"high":23.15,"low":22.6,"close":23.15,"volume":14026517},{"date":"20240729","open":23.45,"high":23.55,"low":22.75,"close":22.75,"volume":14275506},{"date":"20240730","open":22.75,"high":23.0,"low":22.3,"close":23.0,"volume":15096393},{"date":"20240731","open":22.75,"high":23.3,"low":22.7,"close":23.0,"volume":8513820},{"date":"20240801","open":23.45,"high":23.8,"low":23.25,"close":23.75,"volume":13498192},{"date":"20240802","open":23.25,"high":23.6,"low":23.0,"close":23.2,"volume":14461486},{"date":"20240805","open":22.6,"high":22.65,"low":20.9,"close":20.95,"volume":43266129},{"date":"20240806","open":21.1,"high":21.4,"low":19.65,"close":20.35,"volume":32077790},{"date":"20240807","open":20.5,"high":21.5,"low":20.5,"close":21.3,"volume":18052037},{"date":"20240808","open":20.65,"high":21.2,"low":20.6,"close":20.85,"volume":10530649},{"date":"20240809","open":21.25,"high":21.85,"low":21.15,"close":21.45,"volume":19266555},{"date":"20240812","open":21.7,"high":22.2,"low":21.65,"close":22.0,"volume":9763402},{"date":"20240813","open":22.2,"high":22.2,"low":21.65,"close":21.85,"volume":9013345},{"date":"20240814","open":22.2,"high":22.55,"low":22.05,"close":22.2,"volume":11312443},{"date":"20240815","open":22.25,"high":22.25,"low":21.85,"close":21.95,"volume":7586631},{"date":"20240816","open":22.35,"high":22.4,"low":22.0,"close":22.05,"volume":9035691},{"date":"20240819","open":21.9,"high":22.15,"low":21.9,"close":22.0,"volume":4840074},{"date":"20240820","open":22.25,"high":22.35,"low":21.95,"close":22.0,"volume":6168646},{"date":"20240821","open":22.0,"high":22.05,"low":21.7,"close":21.75,"volume":8305472},{"date":"20240822","open":21.85,"high":22.1,"low":21.7,"close":21.85,"volume":5778580},{"date":"20240823","open":21.65,"high":21.7,"low":21.25,"close":21.5,"volume":10203327},{"date":"20240826","open":21.6,"high":22.2,"low":21.6,"close":21.85,"volume":9462520},{"date":"20240827","open":21.9,"high":21.9,"low":21.5,"close":21.7,"volume":7616736},{"date":"20240828","open":21.6,"high":21.7,"low":21.45,"close":21.55,"volume":6537929},{"date":"20240829","open":21.35,"high":21.5,"low":21.25,"close":21.5,"volume":6879640},{"date":"20240830","open":21.6,"high":21.75,"low":21.45,"close":21.6,"volume":7924740},{"date":"20240902","open":21.7,"high":21.7,"low":21.15,"close":21.15,"volume":10730730},{"date":"20240903","open":21.2,"high":21.4,"low":20.7,"close":20.7,"volume":12671659},{"date":"20240904","open":19.75,"high":20.05,"low":19.1,"close":19.8,"volume":25292205},{"date":"20240905","open":20.6,"high":21.1,"low":20.3,"close":20.35,"volume":21891981},{"date":"20240906","open":20.65,"high":20.95,"low":20.2,"close":20.3,"volume":15459472},{"date":"20240909","open":19.6,"high":20.1,"low":19.55,"close":20.0,"volume":13967633},{"date":"20240910","open":20.1,"high":20.15,"low":19.6,"close":19.65,"volume":9759196},{"date":"20240911","open":19.8,"high":20.2,"low":19.8,"close":20.0,"volume":9332992},{"date":"20240912","open":20.7,"high":20.7,"low":20.3,"close":20.35,"volume":9305166},{"date":"20240913","open":20.35,"high":20.55,"low":20.3,"close":20.5,"volume":5095779},{"date":"20240916","open":20.6,"high":20.8,"low":20.55,"close":20.8,"volume":7348546},{"date":"20240918","open":20.95,"high":20.95,"low":20.45,"close":20.5,"volume":8155648},{"date":"20240919","open":20.45,"high":20.75,"low":20.3,"close":20.6,"volume":7917782},{"date":"20240920","open":20.85,"high":21.05,"low":20.7,"close":20.7,"volume":11042283},{"date":"20240923","open":20.9,"high":20.95,"low":20.7,"close":20.8,"volume":6727302},{"date":"20240924","open":20.85,"high":20.85,"low":20.6,"close":20.85,"volume":5557674},{"date":"20240925","open":21.05,"high":21.6,"low":21.0,"close":21.35,"volume":16338994},{"date":"20240926","open":21.55,"high":21.65,"low":21.1,"close":21.15,"volume":8345635},{"date":"20240927","open":21.7,"high":22.2,"low":21.65,"close":22.0,"volume":29409144},{"date":"20240930","open":21.8,"high":21.8,"low":21.3,"close":21.6,"volume":12624305},{"date":"20241001","open":21.5,"high":21.5,"low":20.85,"close":20.9,"volume":16240731},{"date":"20241004","open":20.8,"high":20.85,"low":20.3,"close":20.6,"volume":13892942},{"date":"20241007","open":20.65,"high":20.8,"low":20.45,"close":20.7,"volume":8749820},{"date":"20241008","open":20.65,"high":20.7,"low":20.25,"close":20.55,"volume":10801654},{"date":"20241009","open":20.6,"high":20.7,"low":20.1,"close":20.1,"volume":8511957},{"date":"20241011","open":20.3,"high":20.3,"low":20.1,"close":20.15,"volume":5280022},{"date":"20241014","open":20.15,"high":20.2,"low":20.0,"close":20.15,"volume":5498881},{"date":"20241015","open":20.15,"high":20.35,"low":20.15,"close":20.25,"volume":6798807},{"date":"20241016","open":20.05,"high":20.05,"low":19.75,"close":19.85,"volume":14120120},{"date":"20241017","open":19.9,"high":20.4,"low":19.9,"close":20.3,"volume":10867930},{"date":"20241018","open":20.4,"high":20.4,"low":19.9,"close":19.9,"volume":11260228},{"date":"20241021","open":19.95,"high":20.1,"low":19.85,"close":20.05,"volume":8080809},{"date":"20241022","open":20.05,"high":20.2,"low":19.85,"close":20.05,"volume":7223552},{"date":"20241023","open":20.35,"high":20.75,"low":20.0,"close":20.0,"volume":25623247},{"date":"20241024","open":20.05,"high":20.1,"low":19.7,"close":19.7,"volume":15042861},{"date":"20241025","open":19.7,"high":19.8,"low":19.2,"close":19.3,"volume":21715657},{"date":"20241028","open":19.25,"high":19.35,"low":18.75,"close":19.0,"volume":31050359},{"date":"20241029","open":18.9,"high":18.95,"low":18.5,"close":18.55,"volume":16182857},{"date":"20241030","open":18.65,"high":18.75,"low":18.0,"close":18.0,"volume":24767835},{"date":"20241101","open":17.55,"high":18.4,"low":17.35,"close":18.4,"volume":20800560},{"date":"20241104","open":18.4,"high":18.8,"low":18.2,"close":18.35,"volume":15412039},{"date":"20241105","open":18.35,"high":18.45,"low":18.05,"close":18.05,"volume":10102508},{"date":"20241106","open":18.15,"high":18.5,"low":18.0,"close":18.3,"volume":11718786},{"date":"20241107","open":18.25,"high":19.2,"low":18.15,"close":19.0,"volume":14839953},{"date":"20241108","open":19.1,"high":19.15,"low":18.65,"close":18.7,"volume":10300059},{"date":"20241111","open":18.7,"high":18.7,"low":18.15,"close":18.2,"volume":11850798},{"date":"20241112","open":18.0,"high":18.2,"low":17.8,"close":17.8,"volume":16076333},{"date":"20241113","open":17.8,"high":18.05,"low":17.6,"close":17.8,"volume":10488458},{"date":"20241114","open":17.8,"high":17.9,"low":17.45,"close":17.45,"volume":13661523},{"date":"20241115","open":17.5,"high":18.05,"low":17.5,"close":17.9,"volume":7475316},{"date":"20241118","open":18.0,"high":18.2,"low":17.9,"close":18.15,"volume":8291634},{"date":"20241119","open":18.15,"high":18.3,"low":17.9,"close":18.05,"volume":7402084},{"date":"20241120","open":18.05,"high":18.15,"low":17.7,"close":17.7,"volume":8612861},{"date":"20241121","open":17.7,"high":17.85,"low":17.6,"close":17.75,"volume":10571845},{"date":"20241122","open":17.7,"high":17.85,"low":17.6,"close":17.6,"volume":16593126},{"date":"20241125","open":17.75,"high":17.9,"low":17.45,"close":17.6,"volume":16944810},{"date":"20241126","open":17.65,"high":18.1,"low":17.45,"close":17.95,"volume":16227494},{"date":"20241127","open":17.95,"high":18.0,"low":17.15,"close":17.15,"volume":22571491},{"date":"20241128","open":17.2,"high":17.3,"low":16.4,"close":16.6,"volume":26813425},{"date":"20241129","open":16.7,"high":17.0,"low":16.65,"close":16.95,"volume":14839903},{"date":"20241202","open":17.1,"high":17.2,"low":16.65,"close":16.65,"volume":12255305},{"date":"20241203","open":16.85,"high":17.05,"low":16.7,"close":16.85,"volume":11440492},{"date":"20241204","open":16.95,"high":17.1,"low":16.8,"close":17.1,"volume":9026677},{"date":"20241205","open":17.05,"high":17.1,"low":16.7,"close":16.7,"volume":8899754},{"date":"20241206","open":16.75,"high":17.1,"low":16.65,"close":16.8,"volume":9555446},{"date":"20241209","open":16.85,"high":17.0,"low":16.5,"close":16.65,"volume":10825445},{"date":"20241210","open":16.7,"high":17.2,"low":16.65,"close":16.7,"volume":8607051},{"date":"20241211","open":16.7,"high":16.7,"low":15.75,"close":15.75,"volume":34456127},{"date":"20241212","open":15.9,"high":16.35,"low":15.5,"close":15.55,"volume":20615045},{"date":"20241213","open":15.6,"high":15.6,"low":15.0,"close":15.05,"volume":33812395},{"date":"20241216","open":15.25,"high":15.55,"low":14.95,"close":15.05,"volume":23585344},{"date":"20241217","open":15.2,"high":15.45,"low":15.05,"close":15.1,"volume":16756681},{"date":"20241218","open":15.15,"high":15.9,"low":15.0,"close":15.65,"volume":24594071},{"date":"20241219","open":15.4,"high":16.2,"low":15.3,"close":15.75,"volume":24061128},{"date":"20241220","open":15.6,"high":15.75,"low":15.3,"close":15.3,"volume":17981173},{"date":"20241223","open":15.5,"high":16.0,"low":15.5,"close":15.9,"volume":20472639},{"date":"20241224","open":16.3,"high":17.3,"low":16.25,"close":16.75,"volume":46016831},{"date":"20241225","open":17.0,"high":17.15,"low":16.45,"close":16.6,"volume":22309051},{"date":"20241226","open":16.7,"high":16.8,"low":16.45,"close":16.5,"volume":9937206},{"date":"20241227","open":16.55,"high":16.55,"low":16.1,"close":16.55,"volume":13411211},{"date":"20241230","open":16.45,"high":16.45,"low":16.0,"close":16.0,"volume":10082830},{"date":"20241231","open":15.9,"high":16.0,"low":15.65,"close":15.9,"volume":10495050},{"date":"20250102","open":15.85,"high":16.1,"low":15.65,"close":15.7,"volume":10265203},{"date":"20250103","open":15.8,"high":16.2,"low":15.6,"close":15.6,"volume":9856123},{"date":"20250106","open":15.8,"high":16.1,"low":15.65,"close":15.85,"volume":13013564},{"date":"20250107","open":16.0,"high":16.2,"low":15.15,"close":15.2,"volume":20483942},{"date":"20250108","open":15.2,"high":15.3,"low":15.05,"close":15.15,"volume":8427400},{"date":"20250109","open":15.1,"high":15.15,"low":14.25,"close":14.3,"volume":28827485},{"date":"20250110","open":14.3,"high":14.6,"low":14.2,"close":14.2,"volume":10512371},{"date":"20250113","open":14.1,"high":14.15,"low":13.5,"close":13.65,"volume":25797589},{"date":"20250114","open":13.85,"high":14.2,"low":13.8,"close":14.1,"volume":13672619},{"date":"20250115","open":14.1,"high":14.4,"low":13.9,"close":14.3,"volume":9148164},{"date":"20250116","open":14.5,"high":14.6,"low":14.35,"close":14.45,"volume":10020765},{"date":"20250117","open":14.45,"high":15.3,"low":14.3,"close":15.0,"volume":25485817},{"date":"20250120","open":16.5,"high":16.5,"low":16.5,"close":16.5,"volume":17148618},{"date":"20250121","open":18.15,"high":18.15,"low":18.15,"close":18.15,"volume":22396856},{"date":"20250122","open":19.95,"high":19.95,"low":19.5,"close":19.95,"volume":83176681},{"date":"20250203","open":19.5,"high":20.7,"low":19.2,"close":20.7,"volume":190140299},{"date":"20250204","open":20.25,"high":20.25,"low":18.65,"close":18.65,"volume":114708343},{"date":"20250205","open":18.8,"high":19.0,"low":18.3,"close":18.55,"volume":53651568},{"date":"20250206","open":18.65,"high":18.85,"low":17.7,"close":18.3,"volume":68508909},{"date":"20250207","open":18.1,"high":18.15,"low":17.5,"close":17.6,"volume":46085161},{"date":"20250210","open":17.3,"high":17.4,"low":16.75,"close":16.85,"volume":47529422},{"date":"20250211","open":17.25,"high":18.25,"low":17.1,"close":17.55,"volume":67853516},{"date":"20250212","open":17.55,"high":17.65,"low":17.2,"close":17.2,"volume":31647361},{"date":"20250213","open":17.45,"high":18.7,"low":17.3,"close":18.15,"volume":73853418},{"date":"20250214","open":17.75,"high":18.55,"low":17.6,"close":18.35,"volume":56873378},{"date":"20250217","open":18.35,"high":18.85,"low":18.0,"close":18.45,"volume":48835974},{"date":"20250218","open":18.45,"high":18.7,"low":18.25,"close":18.45,"volume":26205474},{"date":"20250219","open":18.4,"high":19.1,"low":18.4,"close":18.9,"volume":45924681},{"date":"20250220","open":19.0,"high":19.15,"low":18.4,"close":18.45,"volume":35148279},{"date":"20250221","open":18.35,"high":18.8,"low":18.35,"close":18.65,"volume":22285312},{"date":"20250224","open":18.55,"high":18.85,"low":18.4,"close":18.7,"volume":17302542},{"date":"20250225","open":18.5,"high":19.05,"low":18.4,"close":19.0,"volume":34861968},{"date":"20250226","open":18.85,"high":18.95,"low":18.5,"close":18.5,"volume":27505770},{"date":"20250227","open":18.5,"high":18.75,"low":18.2,"close":18.35,"volume":20065934},{"date":"20250303","open":18.1,"high":18.1,"low":17.6,"close":17.6,"volume":23294496},{"date":"20250304","open":17.2,"high":18.0,"low":17.15,"close":18.0,"volume":15674131},{"date":"20250305","open":17.95,"high":18.6,"low":17.85,"close":18.6,"volume":19073049},{"date":"20250306","open":18.75,"high":18.8,"low":18.05,"close":18.05,"volume":17081790},{"date":"20250307","open":18.0,"high":18.35,"low":17.9,"close":17.95,"volume":13450934},{"date":"20250310","open":18.05,"high":18.95,"low":18.05,"close":18.6,"volume":31038072},{"date":"20250311","open":18.2,"high":18.2,"low":17.65,"close":18.05,"volume":29403015},{"date":"20250312","open":18.05,"high":18.6,"low":17.8,"close":18.3,"volume":29990721},{"date":"20250313","open":18.4,"high":18.5,"low":17.7,"close":17.7,"volume":22753648},{"date":"20250314","open":17.75,"high":18.2,"low":17.55,"close":18.0,"volume":18690090},{"date":"20250317","open":18.2,"high":18.35,"low":17.85,"close":17.95,"volume":14498294},{"date":"20250318","open":18.05,"high":18.25,"low":17.8,"close":17.95,"volume":12140700},{"date":"20250319","open":18.0,"high":18.25,"low":17.8,"close":17.8,"volume":13149613},{"date":"20250320","open":17.95,"high":18.35,"low":17.95,"close":18.15,"volume":14056961},{"date":"20250321","open":18.2,"high":18.2,"low":17.75,"close":17.85,"volume":18093370},{"date":"20250324","open":17.9,"high":18.0,"low":17.6,"close":17.6,"volume":9792739},{"date":"20250325","open":17.75,"high":17.95,"low":17.2,"close":17.2,"volume":14594575},{"date":"20250326","open":17.3,"high":17.55,"low":17.2,"close":17.2,"volume":6964288},{"date":"20250327","open":17.05,"high":17.4,"low":16.8,"close":17.1,"volume":12684620},{"date":"20250328","open":17.0,"high":17.1,"low":16.35,"close":16.35,"volume":16644564},{"date":"20250331","open":15.8,"high":15.85,"low":15.15,"close":15.2,"volume":26359250},{"date":"20250401","open":15.5,"high":15.9,"low":15.4,"close":15.7,"volume":15973426},{"date":"20250402","open":15.7,"high":16.0,"low":15.4,"close":15.85,"volume":13663656},{"date":"20250407","open":14.3,"high":14.3,"low":14.3,"close":14.3,"volume":5712387},{"date":"20250408","open":13.1,"high":13.7,"low":12.9,"close":13.25,"volume":41168839},{"date":"20250409","open":13.1,"high":13.15,"low":11.95,"close":11.95,"volume":40647949},{"date":"20250410","open":13.1,"high":13.1,"low":13.1,"close":13.1,"volume":5038707},{"date":"20250411","open":13.0,"high":13.65,"low":12.3,"close":13.65,"volume":22279088},{"date":"20250414","open":14.0,"high":14.7,"low":13.95,"close":14.2,"volume":26001723},{"date":"20250415","open":14.35,"high":14.5,"low":14.15,"close":14.45,"volume":12059758},{"date":"20250416","open":14.25,"high":14.3,"low":14.0,"close":14.1,"volume":17186096},{"date":"20250417","open":14.0,"high":14.25,"low":13.85,"close":14.1,"volume":9924271},{"date":"20250418","open":14.15,"high":14.4,"low":14.1,"close":14.1,"volume":7579420},{"date":"20250421","open":14.2,"high":14.25,"low":13.8,"close":13.8,"volume":6587557},{"date":"20250422","open":13.7,"high":13.95,"low":13.35,"close":13.7,"volume":8210328},{"date":"20250423","open":14.15,"high":14.55,"low":14.1,"close":14.4,"volume":17546236},{"date":"20250424","open":14.5,"high":14.55,"low":14.0,"close":14.0,"volume":9717104},{"date":"20250425","open":14.3,"high":14.35,"low":13.95,"close":14.0,"volume":10872602},{"date":"20250428","open":14.05,"high":14.2,"low":13.9,"close":14.15,"volume":7653121},{"date":"20250429","open":14.4,"high":14.5,"low":14.1,"close":14.4,"volume":13567135},{"date":"20250430","open":14.4,"high":14.45,"low":14.15,"close":14.15,"volume":10018189},{"date":"20250502","open":14.35,"high":14.4,"low":14.2,"close":14.25,"volume":8399830.0},{"date":"20250505","open":14.4,"high":14.65,"low":13.8,"close":14.1,"volume":13987254.0},{"date":"20250506","open":14.2,"high":14.2,"low":14.0,"close":14.1,"volume":5197943.0},{"date":"20250507","open":14.25,"high":14.35,"low":14.05,"close":14.1,"volume":5756512.0},{"date":"20250508","open":14.2,"high":14.45,"low":14.15,"close":14.15,"volume":7716967.0},{"date":"20250509","open":14.25,"high":14.5,"low":14.15,"close":14.5,"volume":12227068.0},{"date":"20250512","open":14.7,"high":15.3,"low":14.6,"close":15.25,"volume":18341654.0},{"date":"20250513","open":15.95,"high":16.3,"low":15.75,"close":16.0,"volume":32900444.0},{"date":"20250514","open":16.05,"high":16.2,"low":15.7,"close":16.0,"volume":18258839.0},{"date":"20250515","open":16.05,"high":16.1,"low":15.55,"close":15.65,"volume":13942725.0},{"date":"20250516","open":15.6,"high":15.6,"low":15.3,"close":15.3,"volume":13792391.0},{"date":"20250519","open":15.25,"high":15.65,"low":15.1,"close":15.3,"volume":10288972.0},{"date":"20250520","open":15.5,"high":15.75,"low":15.4,"close":15.55,"volume":13634578.0},{"date":"20250521","open":15.55,"high":15.75,"low":15.4,"close":15.7,"volume":8036229.0},{"date":"20250522","open":15.5,"high":15.6,"low":15.3,"close":15.6,"volume":8588527.0},{"date":"20250523","open":15.6,"high":15.65,"low":15.45,"close":15.45,"volume":7955100.0},{"date":"20250526","open":15.55,"high":15.6,"low":15.35,"close":15.45,"volume":7671980.0},{"date":"20250527","open":15.55,"high":15.8,"low":15.4,"close":15.55,"volume":13746014.0},{"date":"20250528","open":15.7,"high":16.1,"low":15.35,"close":15.4,"volume":17800593.0},{"date":"20250529","open":15.65,"high":15.8,"low":15.4,"close":15.5,"volume":12510408.0},{"date":"20250602","open":15.5,"high":15.5,"low":14.75,"close":14.75,"volume":14526068.0},{"date":"20250603","open":15.0,"high":15.15,"low":14.6,"close":14.6,"volume":8709474.0},{"date":"20250604","open":14.75,"high":15.2,"low":14.75,"close":14.9,"volume":10682230.0},{"date":"20250605","open":14.9,"high":15.35,"low":14.8,"close":15.05,"volume":10059778.0},{"date":"20250606","open":15.0,"high":15.75,"low":14.9,"close":15.55,"volume":16650736.0},{"date":"20250609","open":15.65,"high":15.75,"low":15.3,"close":15.65,"volume":12265858.0},{"date":"20250610","open":15.7,"high":16.05,"low":15.65,"close":15.8,"volume":13102421.0},{"date":"20250611","open":15.85,"high":15.9,"low":15.6,"close":15.65,"volume":11261877.0},{"date":"20250612","open":15.65,"high":15.85,"low":15.55,"close":15.8,"volume":11335305.0},{"date":"20250613","open":15.6,"high":15.65,"low":15.0,"close":15.0,"volume":18485913.0},{"date":"20250616","open":15.0,"high":15.15,"low":14.8,"close":14.9,"volume":8070363.0},{"date":"20250617","open":15.1,"high":15.4,"low":14.95,"close":15.0,"volume":9531064.0},{"date":"20250618","open":15.0,"high":16.0,"low":14.95,"close":15.95,"volume":21863527.0},{"date":"20250619","open":16.15,"high":16.15,"low":15.3,"close":15.4,"volume":34636022.0},{"date":"20250620","open":15.35,"high":15.55,"low":14.75,"close":15.0,"volume":21293630.0},{"date":"20250623","open":14.65,"high":14.95,"low":14.5,"close":14.9,"volume":11790846.0},{"date":"20250624","open":15.15,"high":15.5,"low":15.1,"close":15.4,"volume":15503712.0},{"date":"20250625","open":15.6,"high":15.6,"low":15.3,"close":15.4,"volume":11450404.0},{"date":"20250626","open":15.5,"high":15.9,"low":15.4,"close":15.4,"volume":15114744.0},{"date":"20250627","open":15.55,"high":15.75,"low":15.35,"close":15.45,"volume":8993203.0},{"date":"20250630","open":15.45,"high":15.55,"low":15.3,"close":15.4,"volume":7862855.0},{"date":"20250701","open":15.4,"high":15.6,"low":15.35,"close":15.5,"volume":8548031.0},{"date":"20250702","open":15.6,"high":16.05,"low":15.3,"close":16.05,"volume":27204569.0},{"date":"20250703","open":17.2,"high":17.65,"low":16.3,"close":17.65,"volume":99255086.0},{"date":"20250704","open":17.8,"high":18.6,"low":17.4,"close":17.65,"volume":206015674.0},{"date":"20250707","open":17.5,"high":17.5,"low":16.8,"close":17.3,"volume":49693713.0},{"date":"20250708","open":17.2,"high":17.2,"low":16.25,"close":16.25,"volume":46555982.0},{"date":"20250709","open":16.25,"high":16.35,"low":15.85,"close":15.95,"volume":30313845.0},{"date":"20250710","open":16.0,"high":16.15,"low":15.6,"close":15.6,"volume":19567599.0},{"date":"20250711","open":15.7,"high":16.2,"low":15.65,"close":16.15,"volume":22721505.0},{"date":"20250714","open":16.25,"high":16.35,"low":15.9,"close":16.2,"volume":13647353.0},{"date":"20250715","open":16.1,"high":16.4,"low":16.1,"close":16.3,"volume":9673864.0},{"date":"20250716","open":16.2,"high":16.4,"low":16.2,"close":16.25,"volume":11204061.0},{"date":"20250717","open":16.25,"high":16.75,"low":16.15,"close":16.65,"volume":18698631.0},{"date":"20250718","open":16.8,"high":16.95,"low":16.5,"close":16.65,"volume":16691906.0},{"date":"20250721","open":16.6,"high":17.1,"low":16.35,"close":16.85,"volume":21052848.0},{"date":"20250722","open":17.2,"high":17.3,"low":16.1,"close":16.25,"volume":55455873.0},{"date":"20250723","open":15.8,"high":15.8,"low":15.45,"close":15.7,"volume":41659580.0},{"date":"20250724","open":15.65,"high":15.7,"low":15.2,"close":15.25,"volume":29756383.0},{"date":"20250725","open":15.25,"high":15.6,"low":15.2,"close":15.3,"volume":15312006.0},{"date":"20250728","open":15.25,"high":15.35,"low":15.05,"close":15.15,"volume":16377474.0},{"date":"20250729","open":15.15,"high":15.3,"low":14.9,"close":14.9,"volume":18889853.0},{"date":"20250730","open":14.9,"high":15.5,"low":14.8,"close":15.35,"volume":22192466.0},{"date":"20250731","open":15.3,"high":15.35,"low":15.0,"close":15.0,"volume":13978246.0},{"date":"20250801","open":14.8,"high":15.25,"low":14.65,"close":15.25,"volume":12302378.0},{"date":"20250804","open":14.85,"high":15.0,"low":14.7,"close":14.95,"volume":24325554.0},{"date":"20250805","open":15.0,"high":15.6,"low":15.0,"close":15.3,"volume":16284982.0},{"date":"20250806","open":15.3,"high":15.3,"low":14.95,"close":15.05,"volume":12524983.0},{"date":"20250807","open":15.1,"high":15.2,"low":14.85,"close":14.85,"volume":12264942.0},{"date":"20250808","open":14.8,"high":15.25,"low":14.8,"close":14.9,"volume":15406611.0},{"date":"20250811","open":14.95,"high":15.05,"low":14.75,"close":15.0,"volume":10182339.0},{"date":"20250812","open":15.0,"high":15.4,"low":15.0,"close":15.3,"volume":13523023.0},{"date":"20250813","open":15.4,"high":15.7,"low":15.25,"close":15.3,"volume":16756833.0},{"date":"20250814","open":15.3,"high":15.7,"low":15.3,"close":15.6,"volume":17598535.0},{"date":"20250815","open":15.7,"high":15.7,"low":15.4,"close":15.6,"volume":12628189.0},{"date":"20250818","open":15.65,"high":15.9,"low":15.55,"close":15.9,"volume":19004833.0},{"date":"20250819","open":16.0,"high":16.25,"low":15.7,"close":15.9,"volume":13939064.0},{"date":"20250820","open":15.9,"high":15.9,"low":15.35,"close":15.45,"volume":13145177.0},{"date":"20250821","open":15.5,"high":16.0,"low":15.5,"close":15.9,"volume":13533401.0},{"date":"20250822","open":15.9,"high":15.95,"low":15.6,"close":15.7,"volume":8199786.0},{"date":"20250825","open":15.95,"high":16.2,"low":15.8,"close":15.8,"volume":14110976.0},{"date":"20250826","open":15.75,"high":15.9,"low":15.7,"close":15.8,"volume":8063411.0},{"date":"20250827","open":15.95,"high":16.15,"low":15.8,"close":15.85,"volume":12712227.0},{"date":"20250828","open":15.95,"high":16.1,"low":15.85,"close":16.05,"volume":11201897.0},{"date":"20250829","open":16.15,"high":16.5,"low":15.9,"close":15.9,"volume":16472548.0},{"date":"20250901","open":15.9,"high":15.95,"low":15.65,"close":15.75,"volume":8642048.0},{"date":"20250902","open":15.85,"high":16.05,"low":15.35,"close":15.4,"volume":10566333.0},{"date":"20250903","open":15.45,"high":15.7,"low":15.3,"close":15.35,"volume":9065626.0},{"date":"20250904","open":15.5,"high":15.9,"low":15.45,"close":15.7,"volume":10902508.0},{"date":"20250905","open":15.8,"high":16.2,"low":15.75,"close":16.05,"volume":18322440.0},{"date":"20250908","open":16.25,"high":16.95,"low":16.25,"close":16.55,"volume":50800717.0},{"date":"20250909","open":16.55,"high":16.7,"low":16.25,"close":16.5,"volume":15531911.0},{"date":"20250910","open":16.65,"high":16.9,"low":16.3,"close":16.7,"volume":24495267.0},{"date":"20250911","open":16.8,"high":17.4,"low":16.6,"close":17.2,"volume":46594823.0},{"date":"20250912","open":17.5,"high":18.9,"low":17.45,"close":17.95,"volume":201622206.0},{"date":"20250915","open":18.1,"high":18.25,"low":17.6,"close":17.85,"volume":54123964.0},{"date":"20250916","open":17.85,"high":18.9,"low":17.6,"close":18.55,"volume":75708624.0},{"date":"20250917","open":18.6,"high":20.4,"low":18.6,"close":20.4,"volume":163960094.0},{"date":"20250918","open":21.25,"high":22.4,"low":20.95,"close":22.4,"volume":325493680.0},{"date":"20250919","open":22.8,"high":23.15,"low":22.0,"close":22.1,"volume":314213408.0},{"date":"20250922","open":22.05,"high":22.6,"low":21.15,"close":21.35,"volume":137319084.0},{"date":"20250923","open":21.65,"high":23.45,"low":21.65,"close":23.45,"volume":259556236.0},{"date":"20250924","open":23.7,"high":24.7,"low":22.9,"close":23.85,"volume":362241550.0},{"date":"20250925","open":23.0,"high":24.0,"low":22.95,"close":23.1,"volume":122208828.0},{"date":"20250926","open":22.75,"high":23.5,"low":22.2,"close":23.1,"volume":121113225.0},{"date":"20250930","open":25.35,"high":25.4,"low":24.95,"close":25.4,"volume":152664035.0},{"date":"20251001","open":25.4,"high":27.9,"low":25.2,"close":27.9,"volume":404766975.0},{"date":"20251002","open":30.1,"high":30.1,"low":27.4,"close":27.7,"volume":439718290.0},{"date":"20251003","open":27.5,"high":28.4,"low":26.85,"close":27.2,"volume":253574999.0},{"date":"20251007","open":27.8,"high":29.9,"low":27.65,"close":29.9,"volume":366193981.0},{"date":"20251008","open":29.1,"high":31.35,"low":28.55,"close":31.0,"volume":384462583.0},{"date":"20251009","open":31.5,"high":32.0,"low":30.2,"close":30.3,"volume":329804510.0},{"date":"20251013","open":27.55,"high":29.3,"low":27.45,"close":29.25,"volume":205759888.0},{"date":"20251014","open":30.6,"high":31.0,"low":27.3,"close":27.3,"volume":294354305.0},{"date":"20251015","open":28.35,"high":28.45,"low":27.4,"close":27.8,"volume":138777196.0},{"date":"20251016","open":28.5,"high":30.25,"low":28.45,"close":28.8,"volume":292728145.0},{"date":"20251017","open":28.5,"high":30.75,"low":28.3,"close":29.5,"volume":250893662.0},{"date":"20251020","open":30.5,"high":31.3,"low":29.45,"close":30.3,"volume":246606181.0},{"date":"20251021","open":30.45,"high":30.75,"low":29.45,"close":30.7,"volume":182443230.0},{"date":"20251022","open":28.5,"high":29.2,"low":28.0,"close":28.0,"volume":277459776.0},{"date":"20251023","open":27.4,"high":28.9,"low":27.35,"close":28.65,"volume":186811585.0},{"date":"20251027","open":30.5,"high":31.5,"low":30.5,"close":31.5,"volume":347845869.0},{"date":"20251028","open":32.15,"high":33.6,"low":31.5,"close":31.95,"volume":588996015.0},{"date":"20251029","open":32.0,"high":33.4,"low":30.55,"close":32.25,"volume":388352347.0},{"date":"20251030","open":32.9,"high":34.1,"low":32.4,"close":33.05,"volume":407145447.0},{"date":"20251031","open":32.95,"high":33.0,"low":31.5,"close":31.5,"volume":197455702.0},{"date":"20251103","open":31.85,"high":32.45,"low":30.1,"close":30.1,"volume":235952795.0},{"date":"20251104","open":30.3,"high":30.65,"low":29.0,"close":29.05,"volume":177475714.0},{"date":"20251105","open":28.0,"high":30.15,"low":27.9,"close":29.95,"volume":176872426.0},{"date":"20251106","open":30.65,"high":31.5,"low":30.15,"close":31.25,"volume":209909996.0},{"date":"20251107","open":30.8,"high":31.35,"low":30.2,"close":30.55,"volume":121062501.0},{"date":"20251110","open":30.95,"high":32.1,"low":30.0,"close":31.55,"volume":233705451.0},{"date":"20251111","open":31.85,"high":34.4,"low":31.5,"close":33.2,"volume":529164465.0},{"date":"20251112","open":33.45,"high":36.5,"low":32.75,"close":36.5,"volume":499495620.0},{"date":"20251113","open":36.9,"high":37.75,"low":34.8,"close":35.65,"volume":617710393.0},{"date":"20251114","open":33.8,"high":35.3,"low":33.0,"close":34.15,"volume":248325964.0},{"date":"20251117","open":35.85,"high":36.65,"low":34.2,"close":35.0,"volume":265534847.0},{"date":"20251118","open":34.8,"high":37.0,"low":34.55,"close":35.9,"volume":467809288.0},{"date":"20251119","open":35.5,"high":38.45,"low":34.95,"close":35.35,"volume":519343046.0},{"date":"20251120","open":36.85,"high":37.55,"low":33.45,"close":35.4,"volume":497717420.0},{"date":"20251121","open":33.5,"high":34.25,"low":32.0,"close":33.0,"volume":271984541.0},{"date":"20251124","open":33.7,"high":34.3,"low":32.0,"close":32.1,"volume":217048963.0},{"date":"20251125","open":33.6,"high":34.2,"low":33.0,"close":33.3,"volume":174398006.0},{"date":"20251126","open":33.75,"high":33.75,"low":31.0,"close":31.65,"volume":230260670.0},{"date":"20251127","open":32.25,"high":33.3,"low":32.25,"close":33.15,"volume":136640285.0},{"date":"20251128","open":33.3,"high":34.9,"low":32.8,"close":34.1,"volume":208217839.0},{"date":"20251201","open":34.5,"high":35.0,"low":33.1,"close":34.0,"volume":164700403.0},{"date":"20251202","open":34.4,"high":34.5,"low":32.75,"close":32.8,"volume":214310269.0},{"date":"20251203","open":33.0,"high":33.35,"low":32.05,"close":32.1,"volume":123097768.0},{"date":"20251204","open":32.2,"high":32.5,"low":31.45,"close":32.3,"volume":101699922.0},{"date":"20251205","open":32.15,"high":33.1,"low":31.7,"close":32.9,"volume":109410515.0},{"date":"20251208","open":33.35,"high":34.75,"low":33.25,"close":34.15,"volume":251293364.0},{"date":"20251209","open":34.65,"high":35.5,"low":34.3,"close":35.3,"volume":261044778.0},{"date":"20251210","open":35.8,"high":36.5,"low":34.2,"close":34.7,"volume":259847330.0},{"date":"20251211","open":35.2,"high":35.5,"low":33.8,"close":33.8,"volume":149124741.0},{"date":"20251212","open":34.0,"high":35.8,"low":34.0,"close":35.1,"volume":222708400.0},{"date":"20251215","open":34.3,"high":35.25,"low":33.1,"close":34.95,"volume":127423185.0},{"date":"20251216","open":34.7,"high":34.7,"low":33.2,"close":33.8,"volume":123835171.0},{"date":"20251217","open":34.1,"high":35.0,"low":33.3,"close":34.8,"volume":156274375.0},{"date":"20251218","open":34.75,"high":35.9,"low":34.7,"close":35.5,"volume":221716222.0},{"date":"20251219","open":36.65,"high":37.35,"low":35.2,"close":36.8,"volume":336341381.0},{"date":"20251222","open":38.8,"high":40.45,"low":38.75,"close":40.45,"volume":477376736.0},{"date":"20251223","open":41.95,"high":42.2,"low":38.8,"close":39.0,"volume":539300263.0},{"date":"20251224","open":39.35,"high":40.4,"low":38.5,"close":40.4,"volume":261731116.0},{"date":"20251226","open":41.55,"high":42.2,"low":40.0,"close":40.05,"volume":314496918.0},{"date":"20251229","open":40.45,"high":40.65,"low":39.2,"close":39.65,"volume":155446006.0},{"date":"20251230","open":39.7,"high":41.1,"low":39.5,"close":40.25,"volume":210185132.0},{"date":"20251231","open":40.8,"high":41.3,"low":39.55,"close":39.55,"volume":194157015.0},{"date":"20260102","open":39.85,"high":42.2,"low":39.3,"close":42.1,"volume":352857727.0},{"date":"20260105","open":43.6,"high":44.7,"low":42.6,"close":43.45,"volume":389177520.0},{"date":"20260106","open":43.5,"high":47.75,"low":43.1,"close":47.75,"volume":447327296.0},{"date":"20260107","open":50.0,"high":50.5,"low":48.0,"close":49.2,"volume":535325591.0},{"date":"20260108","open":48.6,"high":50.2,"low":47.3,"close":49.65,"volume":310713584.0},{"date":"20260109","open":48.0,"high":49.45,"low":44.7,"close":47.5,"volume":101242544.0},{"date":"20260112","open":49.0,"high":50.0,"low":48.0,"close":49.8,"volume":70940203.0},{"date":"20260113","open":51.0,"high":51.0,"low":48.0,"close":50.7,"volume":73960843.0},{"date":"20260114","open":50.7,"high":51.3,"low":50.1,"close":50.6,"volume":46510142.0},{"date":"20260115","open":51.0,"high":51.3,"low":49.85,"close":51.3,"volume":54236143.0},{"date":"20260116","open":53.0,"high":56.4,"low":52.5,"close":56.4,"volume":110873464.0},{"date":"20260119","open":62.0,"high":62.0,"low":62.0,"close":62.0,"volume":24159520.0},{"date":"20260120","open":58.5,"high":68.2,"low":58.5,"close":68.2,"volume":195267350.0},{"date":"20260121","open":67.0,"high":68.5,"low":61.6,"close":62.6,"volume":182416278.0},{"date":"20260122","open":66.1,"high":66.2,"low":62.7,"close":63.6,"volume":102573491.0},{"date":"20260123","open":64.8,"high":64.8,"low":58.2,"close":58.5,"volume":335348044.0},{"date":"20260126","open":58.5,"high":63.7,"low":58.5,"close":60.6,"volume":316571827.0},{"date":"20260127","open":60.6,"high":62.1,"low":57.7,"close":59.5,"volume":265557670.0},{"date":"20260128","open":61.7,"high":65.4,"low":61.7,"close":65.4,"volume":361651007.0},{"date":"20260129","open":67.0,"high":69.5,"low":63.3,"close":65.1,"volume":592076349.0},{"date":"20260130","open":65.1,"high":70.7,"low":65.1,"close":69.5,"volume":502280824.0},{"date":"20260202","open":66.3,"high":66.9,"low":62.6,"close":62.6,"volume":282567486.0},{"date":"20260203","open":66.0,"high":67.4,"low":57.9,"close":59.7,"volume":308535252.0},{"date":"20260204","open":60.0,"high":65.6,"low":59.9,"close":65.6,"volume":223557376.0},{"date":"20260205","open":63.0,"high":64.7,"low":61.5,"close":62.8,"volume":203499311.0},{"date":"20260206","open":62.7,"high":66.3,"low":60.0,"close":63.5,"volume":340736299.0},{"date":"20260209","open":67.8,"high":68.5,"low":63.7,"close":63.8,"volume":294168948.0},{"date":"20260210","open":64.3,"high":65.9,"low":62.6,"close":64.3,"volume":192703938.0},{"date":"20260211","open":63.0,"high":65.5,"low":62.8,"close":63.1,"volume":214396111.0},{"date":"20260223","open":65.8,"high":68.9,"low":65.3,"close":67.0,"volume":257714887.0},{"date":"20260224","open":67.9,"high":73.7,"low":66.1,"close":73.7,"volume":337047858.0},{"date":"20260225","open":74.7,"high":77.0,"low":72.6,"close":76.8,"volume":487502723.0},{"date":"20260226","open":76.8,"high":78.9,"low":75.4,"close":76.7,"volume":322304137.0},{"date":"20260302","open":71.4,"high":77.8,"low":71.4,"close":74.8,"volume":248095174.0},{"date":"20260303","open":76.2,"high":77.0,"low":67.4,"close":68.2,"volume":373534446.0},{"date":"20260304","open":63.2,"high":65.4,"low":61.4,"close":61.4,"volume":210778981.0},{"date":"20260305","open":66.4,"high":67.4,"low":63.4,"close":64.4,"volume":211842643.0},{"date":"20260306","open":63.9,"high":66.3,"low":63.3,"close":64.3,"volume":144135138.0},{"date":"20260309","open":58.0,"high":59.4,"low":57.9,"close":59.4,"volume":135415285.0},{"date":"20260310","open":63.8,"high":64.2,"low":60.5,"close":62.2,"volume":140297005.0},{"date":"20260311","open":64.0,"high":67.5,"low":63.5,"close":66.3,"volume":169992993.0},{"date":"20260312","open":66.6,"high":66.8,"low":63.1,"close":63.1,"volume":171086491.0},{"date":"20260313","open":62.0,"high":64.8,"low":61.9,"close":64.3,"volume":135963192.0},{"date":"20260316","open":65.7,"high":67.4,"low":65.1,"close":65.2,"volume":254597003.0},{"date":"20260317","open":67.1,"high":71.7,"low":66.8,"close":71.7,"volume":393355372.0},{"date":"20260318","open":76.0,"high":76.2,"low":70.7,"close":71.9,"volume":404267429.0},{"date":"20260319","open":70.1,"high":77.8,"low":68.6,"close":75.0,"volume":513362980.0},{"date":"20260320","open":77.1,"high":78.0,"low":71.7,"close":75.5,"volume":529033042.0},{"date":"20260323","open":71.0,"high":72.3,"low":68.6,"close":69.1,"volume":243486481.0},{"date":"20260324","open":71.3,"high":71.4,"low":62.5,"close":62.7,"volume":369690172.0},{"date":"20260325","open":64.1,"high":66.2,"low":62.1,"close":65.0,"volume":278832681.0},{"date":"20260326","open":65.3,"high":67.5,"low":62.8,"close":62.8,"volume":289190595.0},{"date":"20260327","open":60.5,"high":61.2,"low":57.1,"close":59.2,"volume":222663654.0},{"date":"20260330","open":57.5,"high":60.1,"low":57.0,"close":58.1,"volume":206031533.0},{"date":"20260331","open":55.0,"high":55.7,"low":52.4,"close":53.1,"volume":207091698.0},{"date":"20260401","open":57.0,"high":57.0,"low":54.3,"close":54.9,"volume":148151777.0},{"date":"20260402","open":56.5,"high":57.2,"low":53.5,"close":53.5,"volume":155762985.0},{"date":"20260407","open":55.0,"high":55.4,"low":52.7,"close":54.0,"volume":96302858.0},{"date":"20260408","open":55.9,"high":57.9,"low":55.8,"close":57.6,"volume":115253686.0},{"date":"20260409","open":58.0,"high":58.0,"low":53.8,"close":54.0,"volume":134072246.0},{"date":"20260410","open":54.9,"high":57.0,"low":54.1,"close":55.4,"volume":134034940.0},{"date":"20260413","open":55.4,"high":55.5,"low":53.6,"close":54.5,"volume":101937555.0},{"date":"20260414","open":55.5,"high":56.4,"low":54.5,"close":54.6,"volume":109787192.0},{"date":"20260415","open":55.8,"high":56.2,"low":53.1,"close":53.2,"volume":101747295.0},{"date":"20260416","open":53.3,"high":54.3,"low":52.4,"close":54.0,"volume":85975346.0},{"date":"20260417","open":53.6,"high":54.3,"low":52.5,"close":52.6,"volume":87074889.0},{"date":"20260420","open":52.7,"high":52.9,"low":51.0,"close":51.4,"volume":99368654.0},{"date":"20260421","open":52.5,"high":54.3,"low":52.5,"close":54.0,"volume":109355837.0},{"date":"20260422","open":56.0,"high":58.5,"low":54.9,"close":57.0,"volume":219996918.0},{"date":"20260423","open":58.9,"high":59.1,"low":52.0,"close":52.9,"volume":209440294.0},{"date":"20260424","open":53.8,"high":53.8,"low":51.6,"close":52.9,"volume":81283272.0},{"date":"20260427","open":53.3,"high":56.2,"low":53.0,"close":54.5,"volume":145171547.0},{"date":"20260428","open":55.2,"high":55.7,"low":54.2,"close":55.0,"volume":101666278.0},{"date":"20260429","open":54.8,"high":55.2,"low":53.5,"close":53.5,"volume":63666631.0},{"date":"20260430","open":53.9,"high":54.0,"low":51.8,"close":51.9,"volume":94428431.0},{"date":"20260504","open":52.7,"high":53.5,"low":51.6,"close":53.1,"volume":97020345},{"date":"20260505","open":53.4,"high":55.5,"low":52.9,"close":55.4,"volume":106346121},{"date":"20260506","open":53.4,"high":55.5,"low":52.9,"close":55.4,"volume":106346121.0},{"date":"20260507","open":58.8,"high":59.8,"low":56.3,"close":58.1,"volume":255770836.0},{"date":"20260508","open":60.5,"high":63.9,"low":58.0,"close":63.9,"volume":312338758.0},{"date":"20260511","open":65.0,"high":66.5,"low":60.1,"close":61.4,"volume":442180347.0},{"date":"20260512","open":64.9,"high":66.0,"low":62.5,"close":62.5,"volume":283121477.0},{"date":"20260513","open":60.7,"high":60.8,"low":59.0,"close":60.5,"volume":118112300.0},{"date":"20260514","open":61.8,"high":63.4,"low":60.8,"close":62.2,"volume":196451270.0},{"date":"20260515","open":63.0,"high":67.0,"low":62.3,"close":62.8,"volume":356822147.0},{"date":"20260518","open":62.0,"high":63.1,"low":59.2,"close":62.0,"volume":127532182.0},{"date":"20260519","open":61.5,"high":62.3,"low":58.1,"close":58.5,"volume":143820864.0},{"date":"20260520","open":58.7,"high":59.4,"low":56.6,"close":57.8,"volume":84341651.0},{"date":"20260521","open":59.3,"high":61.2,"low":58.9,"close":59.1,"volume":96108084.0},{"date":"20260522","open":60.3,"high":64.8,"low":60.2,"close":63.8,"volume":218295235.0}],"market":"上市","last_updated":"20260523213724"}